<?xml version="1.0" encoding="UTF-8"?>
<?xml-model href="../resources/wlv-label-schema.rng" type="application/xml" schematypens="http://relaxng.org/ns/structure/1.0"?>
<wlv labelID="MSR-0001">
  <metadata>
    <collection collectionID="MSR"></collection>
    <curation curatorID="#cs" curationDate="2022-06-23" />
    <licence licenceScope="all" licenceAbbr="CC BY" uri="https://creativecommons.org/licenses/by/4.0/" />
  </metadata>
    <label labelPosition="front">
      <physical shape="rectangle"/>
      <visual>
        <figure>
          <figureItem norm="Fauna: Katze (Q146)"/>
        </figure>
      </visual>
      <textual>
        <location>Mosel-Saar-Ruwer</location>
        <wineMillesime>1957er</wineMillesime>
        <wineName>
          <location>Zeller</location>
          <location>schwarze Katz</location>
        </wineName>
      </textual>
    </label>
</wlv>
