<?xml version="1.0" encoding="UTF-8"?>
<?xml-model href="../schemas/wlv-label-schema.rng" type="application/xml" schematypens="http://relaxng.org/ns/structure/1.0"?>
<wlv labelID="mwa-graach-0005">
  <metadata>
    <collection collectionID="mwa"/>
    <curation curatorID="#sts" curationDate="2020-11-05" />
    <licence licenceScope="metadata" licenceAbbr="CC BY" url="https://creativecommons.org/licenses/by/4.0/" />
  </metadata>
  <label labelType="Ortsetikett">
    <labelPart partType="front" partNum="1">
      <physical sizeH="tbc" sizeV="tbc" shape="rectangle" material="paper" />
      <visual>
        <frame frameStyle="band" frameColor="blue" frameType="outer">light blue</frame>
        <frame frameStyle="pattern" frameColor="brown" frameType="inner">dark brown</frame>
        <background backgroundStyle="color">light blue</background>
        <figure figureType="abstract" figureNum="1">Ornaments on the four corners of the inner frame</figure>
        <figure figureType="abstract" figureNum="2" figurePosition="center-across">Floral ornament</figure>
        <figure figureType="abstract" figureNum="3" figurePosition="lower-across">Two floral ornaments on the left and right side</figure>
      </visual>
      <textual>
        <wineMillesime wineMillesimeNorm="1874">1874r.</wineMillesime>
        <wineOrigin wineOriginType="locality (Ort)" wineOriginLocality="Graach" ref="wikidata:Q648808">Graacher</wineOrigin>
        <qualityGrapes qualityGrapesNorm="Auslese">Auslese</qualityGrapes>
      </textual>
    </labelPart>
  </label>
</wlv>
